{
  "kind": "singleType",
  "collectionName": "pages_explorer_organisationss",
  "info": {
    "singularName": "pages-explorer-organisations",
    "pluralName": "pages-explorer-organisationss",
    "displayName": "Pages/Explorer/Organisations",
    "description": ""
  },
  "options": {
    "draftAndPublish": true
  },
  "pluginOptions": {
    "i18n": {
      "localized": true
    }
  },
  "attributes": {
    "title": {
      "pluginOptions": {
        "i18n": {
          "localized": true
        }
      },
      "type": "string"
    },
    "subTitle": {
      "pluginOptions": {
        "i18n": {
          "localized": true
        }
      },
      "type": "text"
    },
    "exploreAllText": {
      "pluginOptions": {
        "i18n": {
          "localized": true
        }
      },
      "type": "string"
    },
    "monthItemText": {
      "pluginOptions": {
        "i18n": {
          "localized": true
        }
      },
      "type": "string"
    },
    "monthItemButtonText": {
      "pluginOptions": {
        "i18n": {
          "localized": true
        }
      },
      "type": "string"
    }
  }
}
